syndisco/__init__.py
syndisco/_file_util.py
syndisco/actors.py
syndisco/experiments.py
syndisco/jobs.py
syndisco/logging_util.py
syndisco/model.py
syndisco/postprocessing.py
syndisco/turn_manager.py
syndisco-2.0.6.dist-info/METADATA
syndisco-2.0.6.dist-info/WHEEL
syndisco-2.0.6.dist-info/licenses/LICENSE
syndisco-2.0.6.dist-info/RECORD
