Metadata-Version: 2.4
Name: syndisco
Version: 2.0.6
Summary: Automated experiment creation and execution using LLM agents
Project-URL: Homepage, https://github.com/dimits-ts/synthetic_discussion_framework
Project-URL: Issues, https://github.com/dimits-ts/synthetic_discussion_framework/issues
Author-email: Dimitris Tsirmpas <dim.tsirmaps@aueb.gr>
License-Expression: GPL-3.0
License-File: LICENSE
Keywords: discussion,gpt,large language models,llm,llm agents,llms,local,openai,self-hosting,synthetic
Classifier: Development Status :: 3 - Alpha
Classifier: Environment :: GPU :: NVIDIA CUDA :: 11.8
Classifier: Intended Audience :: Science/Research
Classifier: License :: OSI Approved :: GNU General Public License v3 (GPLv3)
Classifier: Operating System :: OS Independent
Classifier: Programming Language :: Python :: 3
Classifier: Topic :: Scientific/Engineering :: Artificial Intelligence
Classifier: Topic :: Software Development :: Libraries :: Python Modules
Classifier: Topic :: Software Development :: Version Control :: Git
Classifier: Typing :: Typed
Requires-Python: >=3.12
Requires-Dist: accelerate>=0.26.0
Requires-Dist: bitsandbytes
Requires-Dist: coloredlogs
Requires-Dist: pandas
Requires-Dist: torch
Requires-Dist: tqdm
Requires-Dist: transformers
Provides-Extra: dev
Requires-Dist: build; extra == 'dev'
Requires-Dist: ipywidgets; extra == 'dev'
Requires-Dist: myst-parser; extra == 'dev'
Requires-Dist: nbsphinx; extra == 'dev'
Requires-Dist: notebook; extra == 'dev'
Requires-Dist: pandoc; extra == 'dev'
Requires-Dist: sphinx; extra == 'dev'
Requires-Dist: sphinx-autobuild; extra == 'dev'
Requires-Dist: sphinx-rtd-theme; extra == 'dev'
Requires-Dist: twine; extra == 'dev'
